README.md
setup.cfg
setup.py
scripts/vcf_dedupper
vcf_dedup/__init__.py
vcf_dedup/constants.py
vcf_dedup/runner.py
vcf_dedup/tests.py
vcf_dedup.egg-info/PKG-INFO
vcf_dedup.egg-info/SOURCES.txt
vcf_dedup.egg-info/dependency_links.txt
vcf_dedup.egg-info/requires.txt
vcf_dedup.egg-info/top_level.txt
vcf_dedup/tools/__init__.py
vcf_dedup/tools/tests.py
vcf_dedup/tools/variant_comparer.py
vcf_dedup/tools/vcf_sorter.py
vcf_dedup/tools/vcf_transformer.py