Metadata-Version: 1.1
Name: vcf-dedup
Version: 0.4.8
Summary: Removal of duplicated variants from a VCF
Home-page: https://github.com/genomicsengland/vcf-dedup
Author: Pablo Riesgo Ferreiro
Author-email: pablo.riesgo-ferreiro@genomicsengland.co.uk
License: Apache
Download-URL: https://github.com/genomicsengland/vcf-dedup/archive/v0.4.8.tar.gz
Keywords: VCF
Platform: UNKNOWN
Requires: PyVCF
Requires: argparse
